nvcc4jupyter/__init__.py
nvcc4jupyter/parsers.py
nvcc4jupyter/path_utils.py
nvcc4jupyter/plugin.py
nvcc4jupyter/setup_env.py
nvcc4jupyter-1.2.1.dist-info/METADATA
nvcc4jupyter-1.2.1.dist-info/WHEEL
nvcc4jupyter-1.2.1.dist-info/licenses/LICENSE
nvcc4jupyter-1.2.1.dist-info/RECORD
