Metadata-Version: 2.3
Name: nvcc4jupyter
Version: 1.2.1
Summary: Jupyter notebook plugin to run CUDA C/C++ code
Project-URL: documentation, https://nvcc4jupyter.readthedocs.io/
Project-URL: repository, https://github.com/andreinechaev/nvcc4jupyter
Author-email: Andrei Nechaev <lyfaradey@yahoo.com>, Cosmin Stefan Ciocan <ciocan.cosmin98@gmail.com>
License: MIT License
License-File: LICENSE
Classifier: Environment :: GPU
Classifier: Environment :: GPU :: NVIDIA CUDA
Classifier: Framework :: IPython
Classifier: Framework :: Jupyter
Classifier: Programming Language :: Python
Classifier: Programming Language :: Python :: 3
Classifier: Programming Language :: Python :: 3.10
Classifier: Programming Language :: Python :: 3.11
Classifier: Programming Language :: Python :: 3.12
Requires-Python: >=3.10
Provides-Extra: dev
Requires-Dist: ipython>=8.19.0; extra == 'dev'
Requires-Dist: pre-commit>=3.6.0; extra == 'dev'
Requires-Dist: pytest-cov[toml]>=4.1.0; extra == 'dev'
Requires-Dist: pytest>=7.4.3; extra == 'dev'
Provides-Extra: testing
Requires-Dist: ipython>=8.19.0; extra == 'testing'
Requires-Dist: pytest>=7.4.3; extra == 'testing'
